layernext/__init__.py
layernext/datalake/__init__.py
layernext/datalake/annotation.py
layernext/datalake/aws_s3_client.py
layernext/datalake/azure_client.py
layernext/datalake/constants.py
layernext/datalake/datalakeinterface.py
layernext/datalake/dataset.py
layernext/datalake/file_trash.py
layernext/datalake/file_upload.py
layernext/datalake/gcs_client.py
layernext/datalake/ground_truth.py
layernext/datalake/keys.py
layernext/datalake/label.py
layernext/datalake/logger.py
layernext/datalake/metadata.py
layernext/datalake/model_run.py
layernext/datalake/query.py
layernext/datalake/storage_client.py
layernext/datalake/storage_interface.py
layernext/datalake/storage_upload.py
layernext/dataset/__init__.py
layernext/dataset/dataset.py
layernext/dataset/datasetinterface.py
layernext/dataset/logger.py
layernext/dataset/sync.py
layernext/studio/__init__.py
layernext/studio/logger.py
layernext/studio/project.py
layernext/studio/studiointerface.py
layernext_enterprise-1.0.0.dist-info/METADATA
layernext_enterprise-1.0.0.dist-info/WHEEL
layernext_enterprise-1.0.0.dist-info/top_level.txt
layernext_enterprise-1.0.0.dist-info/RECORD
