Metadata-Version: 2.1
Name: layernext-enterprise
Version: 1.0.0
Summary: LayerNext Python SDK
Home-page: UNKNOWN
Author: LayerNext
Author-email: <support@layernext.ai>
License: UNKNOWN
Keywords: python,datalake,datasetsync,ai,annotation,layernext,layernext,machine learning
Platform: UNKNOWN
Classifier: Development Status :: 1 - Planning
Classifier: Intended Audience :: Developers
Classifier: Programming Language :: Python :: 3
Classifier: Operating System :: Unix
Classifier: Operating System :: MacOS :: MacOS X
Classifier: Operating System :: Microsoft :: Windows
Requires-Dist: azure-storage-blob
Requires-Dist: python-dotenv
Requires-Dist: requests
Requires-Dist: uuid
